localpubsub/__init__.py
localpubsub/localpubsub.py
localpubsub-0.0.1.dist-info/METADATA
localpubsub-0.0.1.dist-info/RECORD
localpubsub-0.0.1.dist-info/WHEEL
localpubsub-0.0.1.dist-info/top_level.txt
tests/__init__.py
tests/test_variable_pubsub.py
